CHANGES.md
MANIFEST.in
README.md
development.ini
production.ini
pytest.ini
setup.py
tox.ini
gridix/__init__.py
gridix/routes.py
gridix/security.py
gridix/utils.py
gridix/webapp.py
gridix.web.egg-info/PKG-INFO
gridix.web.egg-info/SOURCES.txt
gridix.web.egg-info/dependency_links.txt
gridix.web.egg-info/entry_points.txt
gridix.web.egg-info/not-zip-safe
gridix.web.egg-info/requires.txt
gridix.web.egg-info/top_level.txt
gridix/api/__init__.py
gridix/api/orgz.py
gridix/api/root.py
gridix/api/security.py
gridix/api/network/__init__.py
gridix/api/network/electric_line.py
gridix/api/network/electric_station.py
gridix/api/network/voltage.py
gridix/data/__init__.py
gridix/data/filters/__init__.py
gridix/data/filters/objects.py
gridix/data/filters/schemas.py
gridix/data/models/__init__.py
gridix/data/models/base.py
gridix/data/models/schemas.py
gridix/data/models/network/__init__.py
gridix/data/models/network/common.py
gridix/data/models/network/segment.py
gridix/data/models/network/structure.py
gridix/export/__init__.py
gridix/export/importer.py
gridix/scripts/__init__.py
gridix/scripts/importdt.py
gridix/scripts/initializedb.py
gridix/scripts/manage_user.py
gridix/views/__init__.py
gridix/views/default.py
gridix/views/helpers.py