Metadata-Version: 1.1
Name: gridix.web
Version: 0.1
Summary: GridIX Web
Home-page: UNKNOWN
Author: Abdul-Hakeem Shaibu
Author-email: s.abdulhakeem@hotmail.com
License: UNKNOWN
Keywords: gridix
Platform: UNKNOWN
Classifier: Programming Language :: Python
Classifier: Framework :: Pyramid
Classifier: Topic :: Internet :: WWW/HTTP
Classifier: Topic :: Internet :: WWW/HTTP :: WSGI :: Application
